langchain_lightdash/__init__.py
langchain_lightdash-0.1.0.dist-info/METADATA
langchain_lightdash-0.1.0.dist-info/WHEEL
langchain_lightdash-0.1.0.dist-info/licenses/LICENSE
langchain_lightdash-0.1.0.dist-info/RECORD
